lambda_setuptools/__init__.py
lambda_setuptools/ldist.py
lambda_setuptools/lupdate.py
lambda_setuptools/lupload.py
lambda_setuptools-0.6.0.dist-info/LICENSE
lambda_setuptools-0.6.0.dist-info/METADATA
lambda_setuptools-0.6.0.dist-info/WHEEL
lambda_setuptools-0.6.0.dist-info/entry_points.txt
lambda_setuptools-0.6.0.dist-info/top_level.txt
lambda_setuptools-0.6.0.dist-info/RECORD
