Metadata-Version: 2.1
Name: lambda-setuptools
Version: 0.6.0
Summary: A Command extension to setuptools that allows building an AWS Lamba dist and uploading to S3
Home-page: https://github.com/QuiNovas/lambda-setuptools
Author: Joseph Wortmann
Author-email: joseph.wortmann@gmail.com
License: APL 2.0
Keywords: setuptools extension
Platform: UNKNOWN
Classifier: Development Status :: 4 - Beta
Classifier: Intended Audience :: Developers
Classifier: Topic :: Software Development :: Libraries :: Python Modules
Classifier: License :: OSI Approved :: Apache Software License
Classifier: Programming Language :: Python :: 3.8
Requires-Dist: boto3
Requires-Dist: setuptools
Requires-Dist: wheel
Requires-Dist: lambda-pkg-resources (>=0.0.5)
